PycordPaginator/PagiNation.py
PycordPaginator/__init__.py
PycordPaginator/errors.py
PycordPaginator-0.0.3.dist-info/LICENSE
PycordPaginator-0.0.3.dist-info/METADATA
PycordPaginator-0.0.3.dist-info/WHEEL
PycordPaginator-0.0.3.dist-info/top_level.txt
PycordPaginator-0.0.3.dist-info/RECORD
